Metadata-Version: 1.0
Name: dash-collapsible-tree
Version: 0.0.7
Summary: A Dash component for reach-collapsible-tree
Home-page: UNKNOWN
Author: Wes Jones <westonkjones@gmail.com>
Author-email: UNKNOWN
License: MIT
Platform: UNKNOWN
